GlobalOptimizationHRLA/__init__.py
GlobalOptimizationHRLA/Algorithms/Algorithm.py
GlobalOptimizationHRLA/Algorithms/HRLA.py
GlobalOptimizationHRLA/Algorithms/OLA.py
GlobalOptimizationHRLA/Algorithms/ULA.py
GlobalOptimizationHRLA/Algorithms/__init__.py
GlobalOptimizationHRLA/PostProcessing/Comparator.py
GlobalOptimizationHRLA/PostProcessing/PostProcessor.py
GlobalOptimizationHRLA/PostProcessing/__init__.py
GlobalOptimizationHRLA/PostProcessing/plot_empirical_probabilities.py
GlobalOptimizationHRLA-1.1.0.dist-info/LICENCE
GlobalOptimizationHRLA-1.1.0.dist-info/METADATA
GlobalOptimizationHRLA-1.1.0.dist-info/WHEEL
GlobalOptimizationHRLA-1.1.0.dist-info/top_level.txt
GlobalOptimizationHRLA-1.1.0.dist-info/RECORD
