Metadata-Version: 2.2
Name: GlobalOptimizationHRLA
Version: 1.1.0
Summary: A package to solve global optimization problems in small dimensions. The method is based on sampling algorithms, and specifically implements the high-resolution Langevin algorithm.
Author-email: Daniel Cortild <d.cortild@rug.nl>
Project-URL: Homepage, https://github.com/DanielCortild/GlobalOptimization
Project-URL: Bug Tracker, https://github.com/DanielCortild/GlobalOptimization/issues
Classifier: Programming Language :: Python :: 3
Classifier: License :: OSI Approved :: MIT License
Classifier: Operating System :: OS Independent
Requires-Python: >=3.8
License-File: LICENCE
Requires-Dist: numpy
Requires-Dist: matplotlib
Requires-Dist: tqdm
Requires-Dist: multiprocess
Requires-Dist: dill
Requires-Dist: matplotlib
Requires-Dist: tabulate
